mvfy/__init__.py
mvfy/data_access/__init__.py
mvfy/data_access/mongobd.py
mvfy/data_access/visual_knowledge_db.py
mvfy/entities/__init__.py
mvfy/entities/visual_knowledge_entities.py
mvfy/use_cases/__init__.py
mvfy/use_cases/visual_knowledge_cases.py
mvfy/utils/__init__.py
mvfy/utils/constants.py
mvfy/utils/feature_flags.py
mvfy/utils/index.py
mvfy/visual/__init__.py
mvfy/visual/func.py
mvfy/visual/middlewares.py
mvfy/visual/detector/__init__.py
mvfy/visual/detector/detectors.py
mvfy/visual/detector/errors.py
mvfy/visual/receiver/__init__.py
mvfy/visual/receiver/errors.py
mvfy/visual/receiver/receivers.py
mvfy/visual/streamer/__init__.py
mvfy/visual/streamer/errors.py
mvfy/visual/streamer/streamer.py
mvfy/visual/systems/__init__.py
mvfy/visual/systems/errors.py
mvfy/visual/systems/image_generator.py
mvfy/visual/systems/visual_knowledge.py
mvfy_visual-0.0.6.dist-info/LICENSE.txt
mvfy_visual-0.0.6.dist-info/METADATA
mvfy_visual-0.0.6.dist-info/WHEEL
mvfy_visual-0.0.6.dist-info/top_level.txt
mvfy_visual-0.0.6.dist-info/RECORD
