Metadata-Version: 2.1
Name: mvfy-visual
Version: 0.0.6
Summary: Package mvfy_visual
Home-page: https://github.com/erwingforerocastro/mvfy_visual
Author: Erwing Forero
Author-email: erwingforerocastro@gmail.com
License: MIT License
Keywords: python,video,streaming,opencv,face recognition,mongodb
Classifier: Development Status :: 3 - Alpha
Classifier: Intended Audience :: Developers
Classifier: Operating System :: Microsoft :: Windows
Classifier: License :: OSI Approved :: MIT License
Classifier: Programming Language :: Python :: 3.9
License-File: LICENSE.txt
